<mvc:View xmlns:mvc="sap.ui.core.mvc" xmlns="sap.m" xmlns:core="sap.ui.core" xmlns:layout="sap.ui.layout" xmlns:uxap="sap.uxap" xmlns:u="sap.ui.unified" controllerName="lifebook.view.main.sidecontent.attachment.Attachment" height="100%">
  <Page showHeader="false">
    <VBox class="sapUiSmallMargin">
      <VBox class="sapUiSmallMarginTop">
        <Label text="{=${selectedAttachments>/}.length} Elemente ausgewählt:"/>
        <List  class="sapUiSmallMarginTop" items="{selectedAttachments>/}">
          <StandardListItem title="{selectedAttachments>name}"/>
        </List>
      </VBox>
    </VBox>
  </Page>
</mvc:View>